mitorch/builders/__init__.py
mitorch/builders/dataloader_builder.py
mitorch/builders/evaluator_builder.py
mitorch/builders/lr_scheduler_builder.py
mitorch/builders/model_builder.py
mitorch/builders/optimizer_builder.py
mitorch/commands/__init__.py
mitorch/commands/agent.py
mitorch/commands/common.py
mitorch/commands/predict.py
mitorch/commands/query.py
mitorch/commands/submit.py
mitorch/commands/train.py
mitorch/common/__init__.py
mitorch/common/environment.py
mitorch/common/job_repository.py
mitorch/common/logger.py
mitorch/common/metrics_repository.py
mitorch/common/mimodel.py
mitorch/common/model_repository.py
mitorch/common/training_config.py
mitorch/datasets/__init__.py
mitorch/datasets/albumentations_transforms.py
mitorch/datasets/factory.py
mitorch/datasets/image_dataset.py
mitorch/datasets/transforms.py
mitorch/evaluators/__init__.py
mitorch/evaluators/evaluator.py
mitorch-0.1.1.dist-info/LICENSE
mitorch-0.1.1.dist-info/METADATA
mitorch-0.1.1.dist-info/WHEEL
mitorch-0.1.1.dist-info/entry_points.txt
mitorch-0.1.1.dist-info/top_level.txt
mitorch-0.1.1.dist-info/RECORD
